Workbook

Sheet Calculador
A1: Intelicampo | C1: Planos
A2: Margem de Lucro | B2: 0 | D2: 50 | E2: 100 | F2: 500 | G2: 1000 | H2: 2000 | I2: > 2,000
A3: Preço da Cabeça Monitorada | D3: 1 | E3: 0.7 | F3: 0.6 | G3: 0.5 | H3: 0.4 | I3: 0.3
A4: Preço Cabeça Mínimo Por Faixa | D4: =0*D3 -> 0 | E4: =(D2+1)*E3 -> 35.7 | F4: =(E2+1)*F3 -> 60.6 | G4: =(F2+1)*G3 -> 250.5 | H4: =(G2+1)*H3 -> 400.4 | I4: =(H2+1)*I3 -> 600.3
A5: Preço Cabeça Máximo Por Faixa | D5: =50*D3 -> 50 | E5: =E2*E3 -> 70 | F5: =F2*F3 -> 300 | G5: =G2*G3 -> 500 | H5: =H2*H3 -> 800 | I5: =I3*$C9 -> 150
A6: Fazendas | B6: 1
A8: Preços | B8: Preço | C8: Rebanho | J8: Total Serviços/Mês
A9: Monitoração Animais/Mês | C9: 500 | D9: =IF(AND($C$9>0,$C$9<=50),$C$9*D3,0) -> 0 | E9: =IF(AND($C$9>50,$C$9<=100),$C$9*E3,0) -> 0 | F9: =IF(AND($C$9>100,$C$9<=500),$C$9*F3,0) -> 300 | G9: =IF(AND($C$9>500,$C$9<=1000),$C$9*G3,0) -> 0 | H9: =IF(AND($C$9>1000,$C$9<=2000),$C$9*H3,0) -> 0 | I9: =IF(AND($C$9>2000),$C$9*I3,0) -> 0 | J9: =SUM(D9:I9) -> 300
A10: Consultoria Inicial/3 dias/mes | B10: 200 | C10: 3 | D10: =IF(D9=0,0,$B10*$C10) -> 0 | E10: =IF(E9=0,0,$B10*$C10) -> 0 | F10: =IF(F9=0,0,$B10*$C10) -> 600 | G10: =IF(G9=0,0,$B10*$C10) -> 0 | H10: =IF(H9=0,0,$B10*$C10) -> 0 | I10: =IF(I9=0,0,$B10*$C10) -> 0 | J10: =SUM(D10:I10) -> 600
A12: Estação de Pesagem | B12: ='Estacao de Pesagerm'!D23*(1+B2) -> 11107 | C12: 1 | D12: =$B12*C12*B6 -> 11107 | E12: =$B12*$B6 -> 11107 | F12: =$B12*$B6 -> 11107 | G12: =$B12*$B6 -> 11107 | H12: =$B12*$B6 -> 11107 | I12: =$B12*$B6 -> 11107
A13: Brincos (R$4,00/brinco) | B13: =4*(1+B2) -> 4 | C13: =I33 | D13: =$B13*$C$9*(1+C13) -> 2000 | E13: =$B13*$C$9 -> 2000 | F13: =$B13*$C$9 -> 2000 | G13: =$B13*$C$9 -> 2000 | H13: =$B13*$C$9 -> 2000 | I13: =$B13*$C$9 -> 2000
A14: Metereologia | B14: =Metereologia!E17*B2 -> 0 | C14: 0 | D14: =$B14*$C$14 -> 0 | E14: =$B14*$C$14 -> 0 | F14: =$B14*$C$14 -> 0 | G14: =$B14*$C$14 -> 0 | H14: =$B14*$C$14 -> 0 | I14: =$B14*$C$14 -> 0
A15: Totem RFID | B15: ='Totem RFID'!E17*(1+B2) -> 4400 | C15: 1 | D15: =$B15*$C$15 -> 4400 | E15: =$B15*$C$15 -> 4400 | F15: =$B15*$C$15 -> 4400 | G15: =$B15*$C$15 -> 4400 | H15: =$B15*$C$15 -> 4400 | I15: =$B15*$C$15 -> 4400
A16: Leitor Manual | B16: ='Leitor Manual'!E18*(1+B2) -> 3920 | C16: 1 | D16: =$B16*$C16 -> 3920 | E16: =$B16*$C16 -> 3920 | F16: =$B16*$C16 -> 3920 | G16: =$B16*$C16 -> 3920 | H16: =$B16*$C16 -> 3920 | I16: =$B16*$C16 -> 3920
A17: WiFi | B17: =WiFi!E17*Calculador!B2 -> 0 | C17: 1 | D17: =$B17*$C$17 -> 0 | E17: =$B17*$C$17 -> 0 | F17: =$B17*$C$17 -> 0 | G17: =$B17*$C$17 -> 0 | H17: =$B17*$C$17 -> 0 | I17: =$B17*$C$17 -> 0
A18: Intelicamp Aquisição de Dados | B18: 600 | C18: 1 | D18: =$B18*$C18*12 -> 7200 | E18: =$B18*$C18*12 -> 7200 | F18: =$B18*$C18*12 -> 7200 | G18: =$B18*$C18*12 -> 7200 | H18: =$B18*$C18*12 -> 7200 | I18: =$B18*$C18*12 -> 7200
A19: Intelicamp Reprodução (mes) | B19: 600 | C19: 0 | D19: =$B19*$C19*12 -> 0 | E19: =$B19*$C19*12 -> 0 | F19: =$B19*$C19*12 -> 0 | G19: =$B19*$C19*12 -> 0 | H19: =$B19*$C19*12 -> 0 | I19: =$B19*$C19*12 -> 0
A20: Intelicamp Manejo (mês) | B20: 600 | C20: 0 | D20: =$B20*$C20*12 -> 0 | E20: =$B20*$C20*12 -> 0 | F20: =$B20*$C20*12 -> 0 | G20: =$B20*$C20*12 -> 0 | H20: =$B20*$C20*12 -> 0 | I20: =$B20*$C20*12 -> 0
A21: Intelicamp Nutrição (mês) | B21: 600 | C21: 0 | D21: =$B21*$C21*12 -> 0 | E21: =$B21*$C21*12 -> 0 | F21: =$B21*$C21*12 -> 0 | G21: =$B21*$C21*12 -> 0 | H21: =$B21*$C21*12 -> 0 | I21: =$B21*$C21*12 -> 0
A22: Intelicamp Leite (mês) | B22: 600 | C22: 0 | D22: =$B22*$C22*12 -> 0 | E22: =$B22*$C22*12 -> 0 | F22: =$B22*$C22*12 -> 0 | G22: =$B22*$C22*12 -> 0 | H22: =$B22*$C22*12 -> 0 | I22: =$B22*$C22*12 -> 0
A23: Intelicampo Finançeiro (mês) | B23: 600 | C23: 0 | D23: =$B23*$C23*12 -> 0 | E23: =$B23*$C23*12 -> 0 | F23: =$B23*$C23*12 -> 0 | G23: =$B23*$C23*12 -> 0 | H23: =$B23*$C23*12 -> 0 | I23: =$B23*$C23*12 -> 0
A24: Intelicampo Inteligencia Artificial | B24: 600 | C24: 0 | D24: =$B24*$C24*12 -> 0 | E24: =$B24*$C24*12 -> 0 | F24: =$B24*$C24*12 -> 0 | G24: =$B24*$C24*12 -> 0 | H24: =$B24*$C24*12 -> 0 | I24: =$B24*$C24*12 -> 0
A25: Instalação (hh) | B25: 100 | C25: 8 | D25: =$B25*$C$25 -> 800 | E25: =$B25*$C$25 -> 800 | F25: =$B25*$C$25 -> 800 | G25: =$B25*$C$25 -> 800 | H25: =$B25*$C$25 -> 800 | I25: =$B25*$C$25 -> 800
A26: Plano de Manutenção Software | B26: 100 | C26: 12 | D26: =$B26*$C$26 -> 1200 | E26: =$B26*$C$26 -> 1200 | F26: =$B26*$C$26 -> 1200 | G26: =$B26*$C$26 -> 1200 | H26: =$B26*$C$26 -> 1200 | I26: =$B26*$C$26 -> 1200
A27: Nuvem | B27: =Nuvem!E17 -> 300 | C27: 1 | D27: =$B27*$C$27*12 -> 3600 | E27: =$B27*$C$27*12 -> 3600 | F27: =$B27*$C$27*12 -> 3600 | G27: =$B27*$C$27*12 -> 3600 | H27: =$B27*$C$27*12 -> 3600 | I27: =$B27*$C$27*12 -> 3600
C29: Planos da Lebov
D30: Gratis | E30: 59 | G30: 199 | H30: 299 | I30: A Combinar

Sheet Estacao de Pesagerm
A1: Módulo de Automação | D1: =SUM(D2:D7) -> 2248
A2: Leitor RFID | B2: 1 | C2: 348 | D2: =B2*C2 -> 348
A3: Processadores | B3: 1 | C3: 300 | D3: =B3*C3 -> 300
A4: Outros circuitos | B4: 1 | C4: 300 | D4: =B4*C4 -> 300
A5: Sensor temperatura | B5: 1 | C5: 500 | D5: 300
A6: Case | B6: 1 | C6: 500 | D6: =B6*C6 -> 500
A7: Montagem do Módulo | B7: 1 | C7: 500 | D7: =B7*C7 -> 500
A8: Estrutura | D8: =SUM(D9:D14) -> 6700
A9: Antena RFID | B9: 1 | C9: 180 | D9: =B9*C9 -> 180
A10: Barras de Pesagem | B10: 1 | C10: 4700 | D10: =B10*C10 -> 4700
A11: Kit solar Komaes e Controlador de carga | B11: 1 | C11: 600 | D11: =B11*C11 -> 600
A12: Bateria 70aH | B12: 1 | C12: 500 | D12: =B12*C12 -> 500
A13: Internet | B13: 1 | C13: 120 | D13: =B13*C13 -> 120
A14: Camera ICSEE externa | B14: 2 | C14: 300 | D14: =B14*C14 -> 600
A15: Passarela | D15: =SUM(D16:D22) -> 4407
A16: Passarela Material | B16: 1 | C16: 1557 | D16: =B16*C16 -> 1557
A17: Pintura Eletroestática | B17: 1 | C17: 1000 | D17: =B17*C17 -> 1000
A18: Fabricação Passarela | B18: 1 | C18: 1000 | D18: =B18*C18 -> 1000
A19: Ferragens | B19: 1 | C19: 50 | D19: =B19*C19 -> 50
A20: Cimentado | B20: 1 | C20: 100 | D20: =B20*C20 -> 100
A21: Pedreiro | B21: 3 | C21: 100 | D21: =B21*C21 -> 300
A22: Poste concreto 7 metros | B22: 1 | C22: 400 | D22: =B22*C22 -> 400
A23: Estação de Pesagem | D23: =SUM(D24:D25) -> 11107
A24: Estrutura | D24: =D8 -> 6700
A25: Passarela | D25: =D15 -> 4407

Sheet Totem RFID
A1: Componente | B1: Modelo | C1: Unitário(R$) | D1: Quantidade | E1: R$ | F1: $ | G1: C$ | H1: Fornecedor
A2: Kit solar Komaes e controlador de carga | C2: 600 | D2: 1 | E2: =C2*D2 -> 600 | F2: =E2*Calculador!B$3 -> 0 | G2: =E2*Calculador!B$4 -> 0 | H2: Mercado Livre
A3: Leitor RFID | B3: cf-mu904 | C3: 300 | D3: 1 | E3: =C3*D3 -> 300 | F3: =E3*Calculador!B$3 -> 0 | G3: =E3*Calculador!B$4 -> 0
A4: Pedestal | C4: 500 | D4: 1 | E4: =C4*D4 -> 500 | F4: =E4*Calculador!B$3 -> 0 | G4: =E4*Calculador!B$4 -> 0
A5: Antena RFID | C5: 200 | D5: 1 | E5: =C5*D5 -> 200 | F5: =E5*Calculador!B$3 -> 0 | G5: =E5*Calculador!B$4 -> 0
A6: Extras | C6: 500 | D6: 1 | E6: =C6*D6 -> 500 | F6: =E6*Calculador!B$3 -> 0 | G6: =E6*Calculador!B$4 -> 0
A7: Bateria | C7: 200 | D7: 1 | E7: =C7*D7 -> 200 | F7: =E7*Calculador!B$3 -> 0 | G7: =E7*Calculador!B$4 -> 0
A8: Eletronica embarcada | C8: 300 | D8: 1 | E8: =C8*D8 -> 300 | F8: =E8*Calculador!B$3 -> 0 | G8: =E8*Calculador!B$4 -> 0
A9: Antena direcional | B9: Mikrotic | C9: 600 | D9: 2 | E9: =C9*D9 -> 1200 | F9: =E9*Calculador!B$3 -> 0 | G9: =E9*Calculador!B$4 -> 0
A10: Roteador Wifi | C10: 100 | D10: 1 | E10: =C10*D10 -> 100 | F10: =E10*Calculador!B$3 -> 0 | G10: =E10*Calculador!B$4 -> 0
E11: =C11*D11 -> 0 | F11: =E11*Calculador!B$3 -> 0 | G11: =E11*Calculador!B$4 -> 0
E12: =C12*D12 -> 0 | F12: =E12*Calculador!B$3 -> 0 | G12: =E12*Calculador!B$4 -> 0
E13: =C13*D13 -> 0 | F13: =E13*Calculador!B$3 -> 0 | G13: =E13*Calculador!B$4 -> 0
E14: =C14*D14 -> 0 | F14: =E14*Calculador!B$3 -> 0 | G14: =E14*Calculador!B$4 -> 0
E15: =C15*D15 -> 0 | F15: =E15*Calculador!B$3 -> 0 | G15: =E15*Calculador!B$4 -> 0
A16: Fabricação | C16: 500 | D16: 1 | E16: =C16*D16 -> 500 | F16: =E16*Calculador!B$3 -> 0 | G16: =E16*Calculador!B$4 -> 0
A17: Total | E17: =SUM(E2:E16) -> 4400 | F17: =SUM(F2:F16) -> 0 | G17: =SUM(G2:G16) -> 0

Sheet Metereologia
A1: Componente | B1: Modelo | C1: Unitário(R$) | D1: Quantidade | E1: R$ | F1: $ | G1: C$ | H1: Fornecedor
A2: BME280 | C2: 32 | D2: 1 | E2: =C2*D2 -> 32 | F2: =E2*Calculador!B$3 -> 0 | G2: =E2*Calculador!B$4 -> 0
A3: ESP | C3: 28 | D3: 1 | E3: =C3*D3 -> 28 | F3: =E3*Calculador!B$3 -> 0 | G3: =E3*Calculador!B$4 -> 0
A4: bateria | C4: 39 | D4: 1 | E4: =C4*D4 -> 39 | F4: =E4*Calculador!B$3 -> 0 | G4: =E4*Calculador!B$4 -> 0
A5: RTC | C5: 12 | D5: 1 | E5: =C5*D5 -> 12 | F5: =E5*Calculador!B$3 -> 0 | G5: =E5*Calculador!B$4 -> 0
A6: Caixa | C6: 15 | D6: 1 | E6: =C6*D6 -> 15 | F6: =E6*Calculador!B$3 -> 0 | G6: =E6*Calculador!B$4 -> 0
A7: Placa | C7: 10 | D7: 1 | E7: =C7*D7 -> 10 | F7: =E7*Calculador!B$3 -> 0 | G7: =E7*Calculador!B$4 -> 0
A8: Conectores e cabos | C8: 15 | D8: 1 | E8: =C8*D8 -> 15 | F8: =E8*Calculador!B$3 -> 0 | G8: =E8*Calculador!B$4 -> 0
E9: =C9*D9 -> 0 | F9: =E9*Calculador!B$3 -> 0 | G9: =E9*Calculador!B$4 -> 0
E10: =C10*D10 -> 0 | F10: =E10*Calculador!B$3 -> 0 | G10: =E10*Calculador!B$4 -> 0
A11: bme280 | C11: 10 | D11: 0 | E11: =C11*D11 -> 0 | F11: =E11*Calculador!B$3 -> 0 | G11: =E11*Calculador!B$4 -> 0 | H11: China
A12: ESP | C12: 12 | D12: 0 | E12: =C12*D12 -> 0 | F12: =E12*Calculador!B$3 -> 0 | G12: =E12*Calculador!B$4 -> 0 | H12: China
A13: bateria | C13: 17 | D13: 0 | E13: =C13*D13 -> 0 | F13: =E13*Calculador!B$3 -> 0 | G13: =E13*Calculador!B$4 -> 0 | H13: China
A14: rtc | C14: 4 | D14: 0 | E14: =C14*D14 -> 0 | F14: =E14*Calculador!B$3 -> 0 | G14: =E14*Calculador!B$4 -> 0 | H14: China
E15: =C15*D15 -> 0 | F15: =E15*Calculador!B$3 -> 0 | G15: =E15*Calculador!B$4 -> 0
A16: Fabricação | C16: 500 | D16: 1 | E16: =C16*D16 -> 500 | F16: =E16*Calculador!B$3 -> 0 | G16: =E16*Calculador!B$4 -> 0
A17: Total | E17: =SUM(E2:E16) -> 651 | F17: =SUM(F2:F16) -> 0 | G17: =SUM(G2:G16) -> 0

Sheet Leitor Manual
A1: Componente | B1: Modelo | C1: Unitário(R$) | D1: Quantidade | E1: R$ | F1: $ | G1: C$ | H1: Fornecedor
A2: Leitor RFID | C2: ='Totem RFID'!C3 -> 300 | D2: 1 | E2: =C2*D2 -> 300 | F2: =E2*Calculador!B$3 -> 0 | G2: =E2*Calculador!B$4 -> 0
A3: Antena | C3: 200 | D3: 1 | E3: =C3*D3 -> 200 | F3: =E3*Calculador!B$3 -> 0 | G3: =E3*Calculador!B$4 -> 0
A4: Celular Android | C4: 2000 | D4: 1 | E4: =C4*D4 -> 2000 | F4: =E4*Calculador!B$3 -> 0 | G4: =E4*Calculador!B$4 -> 0
A5: Case | C5: 500 | D5: 1 | E5: =C5*D5 -> 500 | F5: =E5*Calculador!B$3 -> 0 | G5: =E5*Calculador!B$4 -> 0
A6: Extras | C6: 200 | D6: 1 | E6: =C6*D6 -> 200 | F6: =E6*Calculador!B$3 -> 0 | G6: =E6*Calculador!B$4 -> 0
A7: Bateria 12v | C7: 20 | D7: 1 | E7: =C7*D7 -> 20 | F7: =E7*Calculador!B$3 -> 0 | G7: =E7*Calculador!B$4 -> 0
A8: Eletronica embarcada | C8: 200 | D8: 1 | E8: =C8*D8 -> 200 | F8: =E8*Calculador!B$3 -> 0 | G8: =E8*Calculador!B$4 -> 0
E9: =C9*D9 -> 0 | F9: =E9*Calculador!B$3 -> 0 | G9: =E9*Calculador!B$4 -> 0
E10: =C10*D10 -> 0 | F10: =E10*Calculador!B$3 -> 0 | G10: =E10*Calculador!B$4 -> 0
E11: =C11*D11 -> 0 | F11: =E11*Calculador!B$3 -> 0 | G11: =E11*Calculador!B$4 -> 0
E12: =C12*D12 -> 0 | F12: =E12*Calculador!B$3 -> 0 | G12: =E12*Calculador!B$4 -> 0
E13: =C13*D13 -> 0 | F13: =E13*Calculador!B$3 -> 0 | G13: =E13*Calculador!B$4 -> 0
E14: =C14*D14 -> 0 | F14: =E14*Calculador!B$3 -> 0 | G14: =E14*Calculador!B$4 -> 0
E15: =C15*D15 -> 0 | F15: =E15*Calculador!B$3 -> 0 | G15: =E15*Calculador!B$4 -> 0
E16: =C16*D16 -> 0 | F16: =E16*Calculador!B$3 -> 0 | G16: =E16*Calculador!B$4 -> 0
A17: Fabricação | C17: 500 | D17: 1 | E17: 500 | F17: =E17*Calculador!B$3 -> 0 | G17: =E17*Calculador!B$4 -> 0
A18: Total | E18: =SUM(E2:E17) -> 3920 | F18: =SUM(F2:F17) -> 0 | G18: =SUM(G2:G17) -> 0

Sheet WiFi
A1: Componente | B1: Modelo | C1: Unitário | D1: Quantidade | E1: R$ | F1: $ | G1: C$ | H1: Fornecedor
A2: Antena Mikrotik | B2: STX Lite5 | C2: 450 | D2: 1 | E2: =C2*D2 -> 450 | F2: =E2*Calculador!B$3 -> 0 | G2: =E2*Calculador!B$4 -> 0 | H2: Mercado Livre
A3: Antena Direcional Mikrotik | B3: MT-262006 | C3: 600 | D3: 1 | E3: =C3*D3 -> 600 | F3: =E3*Calculador!B$3 -> 0 | G3: =E3*Calculador!B$4 -> 0 | H3: $150
A4: Repetidor | C4: 200 | D4: 1 | E4: =C4*D4 -> 200 | F4: =E4*Calculador!B$3 -> 0 | G4: =E4*Calculador!B$4 -> 0
A5: Cabo coxeao direta | C5: 120 | D5: 1 | E5: =C5*D5 -> 120 | F5: =E5*Calculador!B$3 -> 0 | G5: =E5*Calculador!B$4 -> 0
E6: =C6*D6 -> 0 | F6: =E6*Calculador!B$3 -> 0 | G6: =E6*Calculador!B$4 -> 0
E7: =C7*D7 -> 0 | F7: =E7*Calculador!B$3 -> 0 | G7: =E7*Calculador!B$4 -> 0
E8: =C8*D8 -> 0 | F8: =E8*Calculador!B$3 -> 0 | G8: =E8*Calculador!B$4 -> 0
E9: =C9*D9 -> 0 | F9: =E9*Calculador!B$3 -> 0 | G9: =E9*Calculador!B$4 -> 0
E10: =C10*D10 -> 0 | F10: =E10*Calculador!B$3 -> 0 | G10: =E10*Calculador!B$4 -> 0
E11: =C11*D11 -> 0 | F11: =E11*Calculador!B$3 -> 0 | G11: =E11*Calculador!B$4 -> 0
E12: =C12*D12 -> 0 | F12: =E12*Calculador!B$3 -> 0 | G12: =E12*Calculador!B$4 -> 0
E13: =C13*D13 -> 0 | F13: =E13*Calculador!B$3 -> 0 | G13: =E13*Calculador!B$4 -> 0
E14: =C14*D14 -> 0 | F14: =E14*Calculador!B$3 -> 0 | G14: =E14*Calculador!B$4 -> 0
E15: =C15*D15 -> 0 | F15: =E15*Calculador!B$3 -> 0 | G15: =E15*Calculador!B$4 -> 0
A16: Fabricação | C16: 500 | D16: 0 | E16: =C16*D16 -> 0 | F16: =E16*Calculador!B$3 -> 0 | G16: =E16*Calculador!B$4 -> 0
A17: Total | E17: =SUM(E2:E16) -> 1370 | F17: =SUM(F2:F16) -> 0 | G17: =SUM(G2:G16) -> 0

Sheet Instalação Campo
A1: Componente | B1: Modelo | C1: Unitário | D1: Quantidade | E1: R$ | F1: $ | G1: C$ | H1: Fornecedor
A2: Câmera | B2: IP Icsee | C2: 300 | D2: 1 | E2: =C2*D2 -> 300 | F2: =E2*Calculador!B$3 -> 0 | G2: =E2*Calculador!B$4 -> 0
A3: Saco de cimento | C3: 30 | D3: 3 | E3: =C3*D3 -> 90 | F3: =E3*Calculador!B$3 -> 0 | G3: =E3*Calculador!B$4 -> 0
A4: Mourões | B4: Madeira | C4: 1 | D4: 0 | E4: =C4*D4 -> 0 | F4: =E4*Calculador!B$3 -> 0 | G4: =E4*Calculador!B$4 -> 0
A5: Arame liso | B5: Metros | C5: 0.5 | D5: 0 | E5: =C5*D5 -> 0 | F5: =E5*Calculador!B$3 -> 0 | G5: =E5*Calculador!B$4 -> 0
A6: Poste Cimento | B6: Galvanizado | C6: 1 | E6: =C6*D6 -> 0 | F6: =E6*Calculador!B$3 -> 0 | G6: =E6*Calculador!B$4 -> 0
A7: Esticadores de fio | C7: 5 | D7: 0 | E7: =C7*D7 -> 0 | F7: =E7*Calculador!B$3 -> 0 | G7: =E7*Calculador!B$4 -> 0
A8: Brita | B8: Kg | C8: 5 | D8: 0 | E8: =C8*D8 -> 0 | F8: =E8*Calculador!B$3 -> 0 | G8: =E8*Calculador!B$4 -> 0
A9: Conduite | B9: Metros | C9: 1 | D9: 0 | E9: =C9*D9 -> 0 | F9: =E9*Calculador!B$3 -> 0 | G9: =E9*Calculador!B$4 -> 0
A10: Disjuntor | C10: 10 | D10: 0 | E10: =C10*D10 -> 0 | F10: =E10*Calculador!B$3 -> 0 | G10: =E10*Calculador!B$4 -> 0
A11: Cabo energia | B11: Metros | C11: 1 | D11: 0 | E11: =C11*D11 -> 0 | F11: =E11*Calculador!B$3 -> 0 | G11: =E11*Calculador!B$4 -> 0
A12: Tela de aço | C12: 1 | D12: 0 | E12: =C12*D12 -> 0 | F12: =E12*Calculador!B$3 -> 0 | G12: =E12*Calculador!B$4 -> 0
A13: Suporte painel solar | C13: 1 | D13: 0 | E13: =C13*D13 -> 0 | F13: =E13*Calculador!B$3 -> 0 | G13: =E13*Calculador!B$4 -> 0
A14: Suporte leitor rfid | C14: 1 | D14: 0 | E14: =C14*D14 -> 0 | F14: =E14*Calculador!B$3 -> 0 | G14: =E14*Calculador!B$4 -> 0
A15: Suporte câmera | C15: 1 | D15: 0 | E15: =C15*D15 -> 0 | F15: =E15*Calculador!B$3 -> 0 | G15: =E15*Calculador!B$4 -> 0
A16: Pintura | C16: 1 | D16: 0 | E16: =C16*D16 -> 0
A18: Mão de Obra | C18: 150 | D18: 3 | E18: =C18*D18 -> 450 | F18: =E18*Calculador!B$3 -> 0 | G18: =E18*Calculador!B$4 -> 0
A19: Total | E19: =SUM(E2:E18) -> 840 | F19: =SUM(F3:F18) -> 0 | G19: =SUM(G3:G18) -> 0

Sheet Nuvem
A1: Componente | B1: Modelo | C1: Unitário | D1: Quantidade | E1: R$ | F1: $ | G1: C$
A2: Azure | B2: CPU | C2: 100 | D2: 1 | E2: =C2*D2 -> 100 | F2: =E2*Calculador!B$3 -> 0 | G2: =E2*Calculador!B$4 -> 0
B3: Armazenamento | C3: 200 | D3: 1 | E3: =C3*D3 -> 200 | F3: =E3*Calculador!B$3 -> 0 | G3: =E3*Calculador!B$4 -> 0
E4: =C4*D4 -> 0 | F4: =E4*Calculador!B$3 -> 0 | G4: =E4*Calculador!B$4 -> 0
E5: =C5*D5 -> 0 | F5: =E5*Calculador!B$3 -> 0 | G5: =E5*Calculador!B$4 -> 0
E6: =C6*D6 -> 0 | F6: =E6*Calculador!B$3 -> 0 | G6: =E6*Calculador!B$4 -> 0
E7: =C7*D7 -> 0 | F7: =E7*Calculador!B$3 -> 0 | G7: =E7*Calculador!B$4 -> 0
E8: =C8*D8 -> 0 | F8: =E8*Calculador!B$3 -> 0 | G8: =E8*Calculador!B$4 -> 0
E9: =C9*D9 -> 0 | F9: =E9*Calculador!B$3 -> 0 | G9: =E9*Calculador!B$4 -> 0
E10: =C10*D10 -> 0 | F10: =E10*Calculador!B$3 -> 0 | G10: =E10*Calculador!B$4 -> 0
E11: =C11*D11 -> 0 | F11: =E11*Calculador!B$3 -> 0 | G11: =E11*Calculador!B$4 -> 0
E12: =C12*D12 -> 0 | F12: =E12*Calculador!B$3 -> 0 | G12: =E12*Calculador!B$4 -> 0
E13: =C13*D13 -> 0 | F13: =E13*Calculador!B$3 -> 0 | G13: =E13*Calculador!B$4 -> 0
E14: =C14*D14 -> 0 | F14: =E14*Calculador!B$3 -> 0 | G14: =E14*Calculador!B$4 -> 0
E15: =C15*D15 -> 0 | F15: =E15*Calculador!B$3 -> 0 | G15: =E15*Calculador!B$4 -> 0
E16: =C16*D16 -> 0 | F16: =E16*Calculador!B$3 -> 0 | G16: =E16*Calculador!B$4 -> 0
A17: Total | E17: =SUM(E2:E16) -> 300 | F17: =SUM(F2:F16) -> 0 | G17: =SUM(G2:G16) -> 0

Sheet Sheet1

Sheet Mercado BR
A1: Estudo de Caso
A2: Participaçã0 (%) | B2: 0.1 | C2: Totem/Fazenda | D2: 1 | E2: Barra de Pesagem/Fazenda | F2: 1 | G2: Instalacão/Fazenda (hr) | H2: 40 | I2: Ambfarm/Fazenda | J2: 1 | K2: Media/Cabeça | L2: 0.5
A3: Consultoria (hr) | B3: 16 hs/fazenda | C3: Leitor Manual/Fazenda | D3: 1 | E3: wifi/Farm | F3: 1 | G3: Estação Pesagem/Fazenda | H3: 1 | I3: Licence/Fazenda | J3: 1 | K3: WIFI: | L3: 1
A6: Estado | B6: Bovinos | C6: Fazendas | D6: Animal/Fazenda | E6: Nossas Fazendas | F6: Nossos Animais | G6: Aquisição de Dados/Ano | H6: Estação de Pesagem | I6: Meteorologia | J6: Totem RFID | K6: Consultoria | L6: Leitor Manual | M6: Wifi | N6: Monitoração Animais* | O6: Total / Estado | P6: Mensal/Estado
A7: Acre | B7: 2139795 | C7: 22649 | D7: =B7/C7 -> 94.476357 | E7: =C7*$B$2% -> 22.649 | F7: =E7*D7 -> 2139.795 | G7: =E7*J$3*12*(1+Calculador!B$18) -> 163344.59 | H7: =E7*H$3*'Estacao de Pesagerm'!D$23*(1+Calculador!B$2) -> 251562.44 | I7: 0 | J7: =E7*D$2*'Totem RFID'!E$17*(1+Calculador!B$2) -> 99655.6 | K7: =E7*Calculador!$J$10*(1+Calculador!B$10) -> 2731469.4 | L7: =E7*D$3*'Leitor Manual'!E$18*(1+Calculador!B$2) -> 88784.08 | M7: 0 | N7: =F7*L$2*12 -> 12838.77 | O7: =SUM(G7:N7) -> 3347654.9 | P7: =O7/12/5 -> 55794.248
A8: Alagoas | B8: 78618 | C8: 42300 | D8: =B8/C8 -> 1.8585816 | E8: =C8*$B$2% -> 42.3 | F8: =E8*D8 -> 78.618 | G8: =E8*J$3*Calculador!B$18*12 -> 304560 | H8: =E8*H$3*'Estacao de Pesagerm'!D$23*(1+Calculador!B$2) -> 469826.1 | I8: 0 | J8: =E8*D$2*'Totem RFID'!E$17*(1+Calculador!B$2) -> 186120 | K8: =E8*Calculador!$J$10*(1+Calculador!B$10) -> 5101380 | L8: =E8*D$3*'Leitor Manual'!E$18*(1+Calculador!B$2) -> 165816 | M8: 0 | N8: =F8*L$2*12 -> 471.708 | O8: =SUM(G8:N8) -> 6228173.8 | P8: =O8/12/5 -> 103802.9
A9: Amapá | B9: 36481 | C9: 684 | D9: =B9/C9 -> 53.334795 | E9: =C9*$B$2% -> 0.684 | F9: =E9*D9 -> 36.481 | G9: =E9*J$3*Calculador!B$18*12 -> 4924.8 | H9: =E9*H$3*'Estacao de Pesagerm'!D$23*(1+Calculador!B$2) -> 7597.188 | I9: 0 | J9: =E9*D$2*'Totem RFID'!E$17*(1+Calculador!B$2) -> 3009.6 | K9: =E9*Calculador!$J$10*(1+Calculador!B$10) -> 82490.4 | L9: =E9*D$3*'Leitor Manual'!E$18*(1+Calculador!B$2) -> 2681.28 | M9: 0 | N9: =F9*L$2*12 -> 218.886 | O9: =SUM(G9:N9) -> 100922.15 | P9: =O9/12/5 -> 1682.0359
A10: Amazonas | B10: 1252385 | C10: 14612 | D10: =B10/C10 -> 85.709348 | E10: =C10*$B$2% -> 14.612 | F10: =E10*D10 -> 1252.385 | G10: =E10*J$3*Calculador!B$18*12 -> 105206.4 | H10: =E10*H$3*'Estacao de Pesagerm'!D$23*(1+Calculador!B$2) -> 162295.48 | I10: 0 | J10: =E10*D$2*'Totem RFID'!E$17*(1+Calculador!B$2) -> 64292.8 | K10: =E10*Calculador!$J$10*(1+Calculador!B$10) -> 1762207.2 | L10: =E10*D$3*'Leitor Manual'!E$18*(1+Calculador!B$2) -> 57279.04 | M10: 0 | N10: =F10*L$2*12 -> 7514.31 | O10: =SUM(G10:N10) -> 2158795.2 | P10: =O10/12/5 -> 35979.921
A11: Bahia | B11: 8177761 | C11: 297284 | D11: =B11/C11 -> 27.508245 | E11: =C11*$B$2% -> 297.284 | F11: =E11*D11 -> 8177.761 | G11: =E11*J$3*Calculador!B$18*12 -> 2140444.8 | H11: =E11*H$3*'Estacao de Pesagerm'!D$23*(1+Calculador!B$2) -> 3301933.4 | I11: 0 | J11: =E11*D$2*'Totem RFID'!E$17*(1+Calculador!B$2) -> 1308049.6 | K11: =E11*Calculador!$J$10*(1+Calculador!B$10) -> 35852450 | L11: =E11*D$3*'Leitor Manual'!E$18*(1+Calculador!B$2) -> 1165353.3 | M11: 0 | N11: =F11*L$2*12 -> 49066.566 | O11: =SUM(G11:N11) -> 43817298 | P11: =O11/12/5 -> 730288.3
A12: Ceará | B12: 1892771 | C12: 114714 | D12: =B12/C12 -> 16.499913 | E12: =C12*$B$2% -> 114.714 | F12: =E12*D12 -> 1892.771 | G12: =E12*J$3*Calculador!B$18*12 -> 825940.8 | H12: =E12*H$3*'Estacao de Pesagerm'!D$23*(1+Calculador!B$2) -> 1274128.4 | I12: 0 | J12: =E12*D$2*'Totem RFID'!E$17*(1+Calculador!B$2) -> 504741.6 | K12: =E12*Calculador!$J$10*(1+Calculador!B$10) -> 13834508 | L12: =E12*D$3*'Leitor Manual'!E$18*(1+Calculador!B$2) -> 449678.88 | M12: 0 | N12: =F12*L$2*12 -> 11356.626 | O12: =SUM(G12:N12) -> 16900355 | P12: =O12/12/5 -> 281672.58
A13: Distrito Federal | B13: 62910 | C13: 1468 | D13: =B13/C13 -> 42.854223 | E13: =C13*$B$2% -> 1.468 | F13: =E13*D13 -> 62.91 | G13: =E13*J$3*Calculador!B$18*12 -> 10569.6 | H13: =E13*H$3*'Estacao de Pesagerm'!D$23*(1+Calculador!B$2) -> 16305.076 | I13: 0 | J13: =E13*D$2*'Totem RFID'!E$17*(1+Calculador!B$2) -> 6459.2 | K13: =E13*Calculador!$J$10*(1+Calculador!B$10) -> 177040.8 | L13: =E13*D$3*'Leitor Manual'!E$18*(1+Calculador!B$2) -> 5754.56 | M13: 0 | N13: =F13*L$2*12 -> 377.46 | O13: =SUM(G13:N13) -> 216506.7 | P13: =O13/12/5 -> 3608.4449
A14: Espírito Santo | B14: 1650374 | C14: 33128 | D14: =B14/C14 -> 49.818099 | E14: =C14*$B$2% -> 33.128 | F14: =E14*D14 -> 1650.374 | G14: =E14*J$3*Calculador!B$18*12 -> 238521.6 | H14: =E14*H$3*'Estacao de Pesagerm'!D$23*(1+Calculador!B$2) -> 367952.7 | I14: 0 | J14: =E14*D$2*'Totem RFID'!E$17*(1+Calculador!B$2) -> 145763.2 | K14: =E14*Calculador!$J$10*(1+Calculador!B$10) -> 3995236.8 | L14: =E14*D$3*'Leitor Manual'!E$18*(1+Calculador!B$2) -> 129861.76 | M14: 0 | N14: =F14*L$2*12 -> 9902.244 | O14: =SUM(G14:N14) -> 4887238.3 | P14: =O14/12/5 -> 81453.972
A15: Goiás | B15: 17292288 | C15: 126100 | D15: =B15/C15 -> 137.13155 | E15: =C15*$B$2% -> 126.1 | F15: =E15*D15 -> 17292.288 | G15: =E15*J$3*Calculador!B$18*12 -> 907920 | H15: =E15*H$3*'Estacao de Pesagerm'!D$23*(1+Calculador!B$2) -> 1400592.7 | I15: 0 | J15: =E15*D$2*'Totem RFID'!E$17*(1+Calculador!B$2) -> 554840 | K15: =E15*Calculador!$J$10*(1+Calculador!B$10) -> 15207660 | L15: =E15*D$3*'Leitor Manual'!E$18*(1+Calculador!B$2) -> 494312 | M15: 0 | N15: =F15*L$2*12 -> 103753.73 | O15: =SUM(G15:N15) -> 18669078 | P15: =O15/12/5 -> 311151.31
A16: Maranhão | B16: 5419044 | C16: 91296 | D16: =B16/C16 -> 59.356861 | E16: =C16*$B$2% -> 91.296 | F16: =E16*D16 -> 5419.044 | G16: =E16*J$3*Calculador!B$18*12 -> 657331.2 | H16: =E16*H$3*'Estacao de Pesagerm'!D$23*(1+Calculador!B$2) -> 1014024.7 | I16: 0 | J16: =E16*D$2*'Totem RFID'!E$17*(1+Calculador!B$2) -> 401702.4 | K16: =E16*Calculador!$J$10*(1+Calculador!B$10) -> 11010298 | L16: =E16*D$3*'Leitor Manual'!E$18*(1+Calculador!B$2) -> 357880.32 | M16: 0 | N16: =F16*L$2*12 -> 32514.264 | O16: =SUM(G16:N16) -> 13473750 | P16: =O16/12/5 -> 224562.51
A17: Mato Grosso | B17: 24309475 | C17: 92723 | D17: =B17/C17 -> 262.17309 | E17: =C17*$B$2% -> 92.723 | F17: =E17*D17 -> 24309.475 | G17: =E17*J$3*Calculador!B$18*12 -> 667605.6 | H17: =E17*H$3*'Estacao de Pesagerm'!D$23*(1+Calculador!B$2) -> 1029874.4 | I17: 0 | J17: =E17*D$2*'Totem RFID'!E$17*(1+Calculador!B$2) -> 407981.2 | K17: =E17*Calculador!$J$10*(1+Calculador!B$10) -> 11182394 | L17: =E17*D$3*'Leitor Manual'!E$18*(1+Calculador!B$2) -> 363474.16 | M17: 0 | N17: =F17*L$2*12 -> 145856.85 | O17: =SUM(G17:N17) -> 13797186 | P17: =O17/12/5 -> 229953.1
A18: Mato Grosso do Sul | B18: 19485201 | C18: 54931 | D18: =B18/C18 -> 354.7214 | E18: =C18*$B$2% -> 54.931 | F18: =E18*D18 -> 19485.201 | G18: =E18*J$3*Calculador!B$18*12 -> 395503.2 | H18: =E18*H$3*'Estacao de Pesagerm'!D$23*(1+Calculador!B$2) -> 610118.62 | I18: 0 | J18: =E18*D$2*'Totem RFID'!E$17*(1+Calculador!B$2) -> 241696.4 | K18: =E18*Calculador!$J$10*(1+Calculador!B$10) -> 6624678.6 | L18: =E18*D$3*'Leitor Manual'!E$18*(1+Calculador!B$2) -> 215329.52 | M18: 0 | N18: =F18*L$2*12 -> 116911.21 | O18: =SUM(G18:N18) -> 8204237.5 | P18: =O18/12/5 -> 136737.29
A19: Minas Gerais | B19: 19575839 | C19: 385488 | D19: =B19/C19 -> 50.781967 | E19: =C19*$B$2% -> 385.488 | F19: =E19*D19 -> 19575.839 | G19: =E19*J$3*Calculador!B$18*12 -> 2775513.6 | H19: =E19*H$3*'Estacao de Pesagerm'!D$23*(1+Calculador!B$2) -> 4281615.2 | I19: 0 | J19: =E19*D$2*'Totem RFID'!E$17*(1+Calculador!B$2) -> 1696147.2 | K19: =E19*Calculador!$J$10*(1+Calculador!B$10) -> 46489853 | L19: =E19*D$3*'Leitor Manual'!E$18*(1+Calculador!B$2) -> 1511113 | M19: 0 | N19: =F19*L$2*12 -> 117455.03 | O19: =SUM(G19:N19) -> 56871697 | P19: =O19/12/5 -> 947861.61
... A32: São Paulo | B32: 8331874 | C32: 107255 | D32: =B32/C32 -> 77.682849 | E32: =C32*$B$2% -> 107.255 | F32: =E32*D32 -> 8331.874 | G32: =E32*J$3*Calculador!B$18*12 -> 772236 | H32: =E32*H$3*'Estacao de Pesagerm'!D$23*(1+Calculador!B$2) -> 1191281.3 | I32: 0 | J32: =E32*D$2*'Totem RFID'!E$17*(1+Calculador!B$2) -> 471922 | K32: =E32*Calculador!$J$10*(1+Calculador!B$10) -> 12934953 | L32: =E32*D$3*'Leitor Manual'!E$18*(1+Calculador!B$2) -> 420439.6 | M32: 0 | N32: =F32*L$2*12 -> 49991.244 | O32: =SUM(G32:N32) -> 15840823 | P32: =O32/12/5 -> 264013.72
A33: Tocantins | B33: 6477537 | C33: 50451 | D33: =B33/C33 -> 128.39264 | E33: =C33*$B$2% -> 50.451 | F33: =E33*D33 -> 6477.537 | G33: =E33*J$3*Calculador!B$18*12 -> 363247.2 | H33: =E33*H$3*'Estacao de Pesagerm'!D$23*Calculador!B$2 -> 0 | I33: 0 | J33: =E33*D$2*'Totem RFID'!E$17*(1+Calculador!B$2) -> 221984.4 | K33: =E33*Calculador!$J$10*(1+Calculador!B$10) -> 6084390.6 | L33: =E33*D$3*'Leitor Manual'!E$18*(1+Calculador!B$2) -> 197767.92 | M33: 0 | N33: =F33*L$2*12 -> 38865.222 | O33: =SUM(G33:N33) -> 6906255.3 | P33: =O33/12/5 -> 115104.26
A34: Totais | B34: =SUM(B7:B33) -> 172011314 | C34: =SUM(C7:C33) -> 2553806 | D34: =B34/C34 -> 67.354887 | E34: =SUM(E7:E33) -> 2553.806 | F34: =SUM(F7:F33) -> 172011.31 | G34: =SUM(G7:G33) -> 18387675 | H34: =SUM(H7:H33) -> 27804764 | I34: =SUM(I7:I33) -> 0 | J34: =SUM(J7:J33) -> 11236746 | K34: =SUM(K7:K33) -> 3.07989e+08 | L34: =SUM(L7:L33) -> 10010920 | ... P34: =SUM(P7:P33) -> 6274352.9
G35: =E34*J3 -> 2553.806 | H35: =E34*J3 -> 2553.806 | I35: =E34*J2 -> 2553.806 | J35: =E34*D2 -> 2553.806 | L35: =E34*D3 -> 2553.806 | M35: =E34*F3 -> 2553.806 | O35: =O34*Calculador!B3 -> 0 | P35: =P34*Calculador!B3 -> 0
O36: =O34*Calculador!B4 -> 0 | P36: =P34*Calculador!B4 -> 0
N38: *Media nacional de 68 animais por fazenda
